rosetta/__init__.py
rosetta/access.py
rosetta/apps.py
rosetta/poutil.py
rosetta/signals.py
rosetta/storage.py
rosetta/translate_utils.py
rosetta/urls.py
rosetta/views.py
rosetta/conf/__init__.py
rosetta/locale/ar/LC_MESSAGES/django.mo
rosetta/locale/ar/LC_MESSAGES/django.po
rosetta/locale/cs/LC_MESSAGES/django.mo
rosetta/locale/cs/LC_MESSAGES/django.po
rosetta/locale/de/LC_MESSAGES/django.mo
rosetta/locale/de/LC_MESSAGES/django.po
rosetta/locale/es/LC_MESSAGES/django.mo
rosetta/locale/es/LC_MESSAGES/django.po
rosetta/locale/fa/LC_MESSAGES/django.mo
rosetta/locale/fa/LC_MESSAGES/django.po
rosetta/locale/fr/LC_MESSAGES/django.mo
rosetta/locale/fr/LC_MESSAGES/django.po
rosetta/locale/hu/LC_MESSAGES/django.mo
rosetta/locale/hu/LC_MESSAGES/django.po
rosetta/locale/it/LC_MESSAGES/django.mo
rosetta/locale/it/LC_MESSAGES/django.po
rosetta/locale/ky/LC_MESSAGES/django.mo
rosetta/locale/ky/LC_MESSAGES/django.po
rosetta/locale/nl/LC_MESSAGES/django.mo
rosetta/locale/nl/LC_MESSAGES/django.po
rosetta/locale/pl/LC_MESSAGES/django.mo
rosetta/locale/pl/LC_MESSAGES/django.po
rosetta/locale/ru/LC_MESSAGES/django.mo
rosetta/locale/ru/LC_MESSAGES/django.po
rosetta/locale/tr/LC_MESSAGES/django.mo
rosetta/locale/tr/LC_MESSAGES/django.po
rosetta/locale/uk/LC_MESSAGES/django.mo
rosetta/locale/uk/LC_MESSAGES/django.po
rosetta/locale/xx/LC_MESSAGES/django.mo
rosetta/locale/xx/LC_MESSAGES/django.po
rosetta/locale/zh_hans/LC_MESSAGES/django.mo
rosetta/locale/zh_hans/LC_MESSAGES/django.po
rosetta/static/admin/img/icon_searchbox_rosetta.png
rosetta/templates/rosetta/admin_index.html
rosetta/templates/rosetta/base.html
rosetta/templates/rosetta/file-list.html
rosetta/templates/rosetta/form.html
rosetta/templates/rosetta/css/rosetta.css
rosetta/templates/rosetta/js/rosetta.js
rosetta/templatetags/__init__.py
rosetta/templatetags/rosetta.py
rosetta/tests/__init__.py
rosetta/tests/django.po.issue186.template
rosetta/tests/django.po.issue24gh.template
rosetta/tests/django.po.issue34gh.template
django_rosetta-0.10.0.dist-info/LICENSE
django_rosetta-0.10.0.dist-info/METADATA
django_rosetta-0.10.0.dist-info/WHEEL
django_rosetta-0.10.0.dist-info/top_level.txt
django_rosetta-0.10.0.dist-info/RECORD
