Metadata-Version: 2.1
Name: django-rosetta
Version: 0.10.0
Summary: A Django application that eases the translation of Django projects
Home-page: https://github.com/mbi/django-rosetta
Author: Marco Bonetti
Author-email: mbonetti@gmail.com
License: MIT
Classifier: Development Status :: 4 - Beta
Classifier: Environment :: Web Environment
Classifier: Intended Audience :: Developers
Classifier: License :: OSI Approved :: MIT License
Classifier: Operating System :: OS Independent
Classifier: Programming Language :: Python
Classifier: Topic :: Software Development :: Localization
Classifier: Topic :: Software Development :: Internationalization
Classifier: Framework :: Django
Classifier: Framework :: Django :: 4.2
Classifier: Framework :: Django :: 5.0
Classifier: Programming Language :: Python :: 3.9
Classifier: Programming Language :: Python :: 3.10
Classifier: Programming Language :: Python :: 3.11
Classifier: Programming Language :: Python :: 3.12
License-File: LICENSE
Requires-Dist: Django>=4.2
Requires-Dist: requests>=2.30.0
Requires-Dist: polib>=1.1.0
